deepolicy/__init__.py
deepolicy/utils.py
deepolicy-0.0.3.dist-info/LICENSE
deepolicy-0.0.3.dist-info/METADATA
deepolicy-0.0.3.dist-info/WHEEL
deepolicy-0.0.3.dist-info/top_level.txt
deepolicy-0.0.3.dist-info/RECORD
