Metadata-Version: 2.1
Name: deepolicy
Version: 0.0.3
Summary: Create the robot`s brain. - deepolicy
Author-email: Xin ZHOU <zhouxin12@nudt.edu.cn>
Project-URL: Homepage, https://deepolicy.cn
Project-URL: Github, https://github.com/deepolicy
Classifier: Programming Language :: Python :: 3
Classifier: License :: OSI Approved :: MIT License
Classifier: Operating System :: OS Independent
Requires-Python: >=3.7
License-File: LICENSE
